concinnity/__init__.py
concinnity/concinnity.cfg
concinnity/concinnity.data
concinnity/concinnity.py
concinnity-0.1.6.dist-info/licenses/LICENSE
concinnity-0.1.6.dist-info/WHEEL
concinnity-0.1.6.dist-info/entry_points.txt
concinnity-0.1.6.dist-info/METADATA
concinnity-0.1.6.dist-info/RECORD
