Metadata-Version: 2.4
Name: concinnity
Version: 0.1.6
Summary: clean and aesthetic CLI counter tool!
License-Expression: GPL-3.0-only
License-File: LICENSE
Requires-Python: >=3.12
